choumine_project_kpi/__init__.py
choumine_project_kpi/__main__.py
choumine_project_kpi/common.py
choumine_project_kpi/tools.py
choumine_project_kpi-0.1.8.dist-info/METADATA
choumine_project_kpi-0.1.8.dist-info/WHEEL
choumine_project_kpi-0.1.8.dist-info/entry_points.txt
choumine_project_kpi-0.1.8.dist-info/RECORD
